[
  {
    "AreaName": "Lambeth",
    "Electorate": 226899,
    "Ballot papers at the count": 71925,
    "Value": 31.7,
    "Time period": 2022
  },
  {
    "AreaName": "London",
    "Electorate": 6036183,
    "Ballot papers at the count": 2151194,
    "Value": 35.6,
    "Time period": 2022
  },
  {
    "AreaName": "Brixton Acre Lane",
    "Electorate": 11042,
    "Ballot papers at the count": 3271,
    "Value": 29.6,
    "Time period": 2022
  },
  {
    "AreaName": "Brixton North",
    "Electorate": 11084,
    "Ballot papers at the count": 2869,
    "Value": 25.9,
    "Time period": 2022
  },
  {
    "AreaName": "Brixton Rush Common",
    "Electorate": 10646,
    "Ballot papers at the count": 3306,
    "Value": 31.1,
    "Time period": 2022
  },
  {
    "AreaName": "Brixton Windrush",
    "Electorate": 6845,
    "Ballot papers at the count": 1858,
    "Value": 27.1,
    "Time period": 2022
  },
  {
    "AreaName": "Clapham Common & Abbeville",
    "Electorate": 7357,
    "Ballot papers at the count": 2908,
    "Value": 39.5,
    "Time period": 2022
  },
  {
    "AreaName": "Clapham East",
    "Electorate": 7439,
    "Ballot papers at the count": 1744,
    "Value": 23.4,
    "Time period": 2022
  },
  {
    "AreaName": "Clapham Park",
    "Electorate": 9710,
    "Ballot papers at the count": 2497,
    "Value": 25.7,
    "Time period": 2022
  },
  {
    "AreaName": "Clapham Town",
    "Electorate": 11514,
    "Ballot papers at the count": 3562,
    "Value": 30.9,
    "Time period": 2022
  },
  {
    "AreaName": "Gipsy Hill",
    "Electorate": 7792,
    "Ballot papers at the count": 2919,
    "Value": 37.5,
    "Time period": 2022
  },
  {
    "AreaName": "Herne Hill & Loughborough Junction",
    "Electorate": 11208,
    "Ballot papers at the count": 4670,
    "Value": 41.7,
    "Time period": 2022
  },
  {
    "AreaName": "Kennington",
    "Electorate": 11498,
    "Ballot papers at the count": 3967,
    "Value": 34.5,
    "Time period": 2022
  },
  {
    "AreaName": "Knight's Hill",
    "Electorate": 11677,
    "Ballot papers at the count": 3707,
    "Value": 31.7,
    "Time period": 2022
  },
  {
    "AreaName": "Myatt's Fields",
    "Electorate": 8138,
    "Ballot papers at the count": 2342,
    "Value": 28.8,
    "Time period": 2022
  },
  {
    "AreaName": "Oval",
    "Electorate": 8998,
    "Ballot papers at the count": 2783,
    "Value": 30.9,
    "Time period": 2022
  },
  {
    "AreaName": "St Martin's",
    "Electorate": 7204,
    "Ballot papers at the count": 2161,
    "Value": 30.0,
    "Time period": 2022
  },
  {
    "AreaName": "Stockwell East",
    "Electorate": 7223,
    "Ballot papers at the count": 2162,
    "Value": 29.9,
    "Time period": 2022
  },
  {
    "AreaName": "Stockwell West & Larkhall",
    "Electorate": 11730,
    "Ballot papers at the count": 3173,
    "Value": 27.1,
    "Time period": 2022
  },
  {
    "AreaName": "Streatham Common & Vale",
    "Electorate": 11872,
    "Ballot papers at the count": 3402,
    "Value": 28.7,
    "Time period": 2022
  },
  {
    "AreaName": "Streatham Hill East",
    "Electorate": 7152,
    "Ballot papers at the count": 2213,
    "Value": 30.9,
    "Time period": 2022
  },
  {
    "AreaName": "Streatham Hill West & Thornton",
    "Electorate": 7934,
    "Ballot papers at the count": 3323,
    "Value": 41.9,
    "Time period": 2022
  },
  {
    "AreaName": "Streatham St Leonard's",
    "Electorate": 10754,
    "Ballot papers at the count": 3655,
    "Value": 34.0,
    "Time period": 2022
  },
  {
    "AreaName": "Streatham Wells",
    "Electorate": 7123,
    "Ballot papers at the count": 2323,
    "Value": 32.6,
    "Time period": 2022
  },
  {
    "AreaName": "Vauxhall",
    "Electorate": 6474,
    "Ballot papers at the count": 1729,
    "Value": 26.7,
    "Time period": 2022
  },
  {
    "AreaName": "Waterloo & South Bank",
    "Electorate": 6158,
    "Ballot papers at the count": 2003,
    "Value": 32.5,
    "Time period": 2022
  },
  {
    "AreaName": "West Dulwich",
    "Electorate": 8327,
    "Ballot papers at the count": 3378,
    "Value": 40.6,
    "Time period": 2022
  },
  {
    "AreaName": "England",
    "Electorate": 22376330,
    "Ballot papers at the count": 7520663,
    "Value": 33.6,
    "Time period": 2022
  },
  {
    "AreaName": "Lambeth",
    "Electorate": 231772,
    "Ballot papers at the count": 78737,
    "Value": 34.0,
    "Time period": 2018
  },
  {
    "AreaName": "London",
    "Electorate": 5944784,
    "Ballot papers at the count": 2320895,
    "Value": 39.0,
    "Time period": 2018
  },
  {
    "AreaName": "England",
    "Electorate": 21476493,
    "Ballot papers at the count": 7461042,
    "Value": 34.7,
    "Time period": 2018
  }
]
