[{"AreaName":"Lambeth","Aged 4 years and under (number)":15265,"Aged 4 years and under (%)":4.8,"Aged 5 to 9 years (number)":14939,"Aged 5 to 9 years (%)":4.7,"Aged 10 to 15 years (number)":18505,"Aged 10 to 15 years (%)":5.8,"Aged 16 to 19 years (number)":11914,"Aged 16 to 19 years (%)":3.8,"Aged 20 to 24 years (number)":26755,"Aged 20 to 24 years (%)":8.4,"Aged 25 to 34 years (number)":81901,"Aged 25 to 34 years (%)":25.8,"Aged 35 to 49 years (number)":69292,"Aged 35 to 49 years (%)":21.8,"Aged 50 to 64 years (number)":51826,"Aged 50 to 64 years (%)":16.3,"Aged 65 to 74 years (number)":15837,"Aged 65 to 74 years (%)":5,"Aged 75 to 84 years (number)":8264,"Aged 75 to 84 years (%)":2.6,"Aged 85 years and over (number)":3164,"Aged 85 years and over (%)":1},{"AreaName":"Brixton Acre Lane","Aged 4 years and under (number)":482,"Aged 4 years and under (%)":3.2,"Aged 5 to 9 years (number)":424,"Aged 5 to 9 years (%)":2.8,"Aged 10 to 15 years (number)":573,"Aged 10 to 15 years (%)":3.8,"Aged 16 to 19 years (number)":326,"Aged 16 to 19 years (%)":2.1,"Aged 20 to 24 years (number)":1679,"Aged 20 to 24 years (%)":11,"Aged 25 to 34 years (number)":5554,"Aged 25 to 34 years (%)":36.4,"Aged 35 to 49 years (number)":2939,"Aged 35 to 49 years (%)":19.3,"Aged 50 to 64 years (number)":2128,"Aged 50 to 64 years (%)":14,"Aged 65 to 74 years (number)":644,"Aged 65 to 74 years (%)":4.2,"Aged 75 to 84 years (number)":351,"Aged 75 to 84 years (%)":2.3,"Aged 85 years and over (number)":146,"Aged 85 years and over (%)":1},{"AreaName":"Brixton North","Aged 4 years and under (number)":656,"Aged 4 years and under (%)":4,"Aged 5 to 9 years (number)":794,"Aged 5 to 9 years (%)":4.9,"Aged 10 to 15 years (number)":1112,"Aged 10 to 15 years (%)":6.8,"Aged 16 to 19 years (number)":765,"Aged 16 to 19 years (%)":4.7,"Aged 20 to 24 years (number)":1578,"Aged 20 to 24 years (%)":9.7,"Aged 25 to 34 years (number)":4068,"Aged 25 to 34 years (%)":24.9,"Aged 35 to 49 years (number)":3300,"Aged 35 to 49 years (%)":20.2,"Aged 50 to 64 years (number)":2823,"Aged 50 to 64 years (%)":17.3,"Aged 65 to 74 years (number)":722,"Aged 65 to 74 years (%)":4.4,"Aged 75 to 84 years (number)":378,"Aged 75 to 84 years (%)":2.3,"Aged 85 years and over (number)":125,"Aged 85 years and over (%)":0.8},{"AreaName":"Brixton Rush Common","Aged 4 years and under (number)":752,"Aged 4 years and under (%)":5,"Aged 5 to 9 years (number)":749,"Aged 5 to 9 years (%)":5,"Aged 10 to 15 years (number)":968,"Aged 10 to 15 years (%)":6.5,"Aged 16 to 19 years (number)":592,"Aged 16 to 19 years (%)":4,"Aged 20 to 24 years (number)":1074,"Aged 20 to 24 years (%)":7.2,"Aged 25 to 34 years (number)":3908,"Aged 25 to 34 years (%)":26.2,"Aged 35 to 49 years (number)":3217,"Aged 35 to 49 years (%)":21.5,"Aged 50 to 64 years (number)":2562,"Aged 50 to 64 years (%)":17.2,"Aged 65 to 74 years (number)":657,"Aged 65 to 74 years (%)":4.4,"Aged 75 to 84 years (number)":325,"Aged 75 to 84 years (%)":2.2,"Aged 85 years and over (number)":125,"Aged 85 years and over (%)":0.8},{"AreaName":"Brixton Windrush","Aged 4 years and under (number)":406,"Aged 4 years and under (%)":4.3,"Aged 5 to 9 years (number)":391,"Aged 5 to 9 years (%)":4.1,"Aged 10 to 15 years (number)":448,"Aged 10 to 15 years (%)":4.7,"Aged 16 to 19 years (number)":359,"Aged 16 to 19 years (%)":3.8,"Aged 20 to 24 years (number)":1020,"Aged 20 to 24 years (%)":10.8,"Aged 25 to 34 years (number)":2863,"Aged 25 to 34 years (%)":30.2,"Aged 35 to 49 years (number)":1787,"Aged 35 to 49 years (%)":18.8,"Aged 50 to 64 years (number)":1584,"Aged 50 to 64 years (%)":16.7,"Aged 65 to 74 years (number)":355,"Aged 65 to 74 years (%)":3.7,"Aged 75 to 84 years (number)":213,"Aged 75 to 84 years (%)":2.2,"Aged 85 years and over (number)":56,"Aged 85 years and over (%)":0.6},{"AreaName":"Clapham Common & Abbeville","Aged 4 years and under (number)":508,"Aged 4 years and under (%)":5.1,"Aged 5 to 9 years (number)":430,"Aged 5 to 9 years (%)":4.3,"Aged 10 to 15 years (number)":487,"Aged 10 to 15 years (%)":4.9,"Aged 16 to 19 years (number)":206,"Aged 16 to 19 years (%)":2.1,"Aged 20 to 24 years (number)":1018,"Aged 20 to 24 years (%)":10.2,"Aged 25 to 34 years (number)":3241,"Aged 25 to 34 years (%)":32.4,"Aged 35 to 49 years (number)":1976,"Aged 35 to 49 years (%)":19.7,"Aged 50 to 64 years (number)":1378,"Aged 50 to 64 years (%)":13.8,"Aged 65 to 74 years (number)":453,"Aged 65 to 74 years (%)":4.5,"Aged 75 to 84 years (number)":220,"Aged 75 to 84 years (%)":2.2,"Aged 85 years and over (number)":101,"Aged 85 years and over (%)":1},{"AreaName":"Clapham East","Aged 4 years and under (number)":368,"Aged 4 years and under (%)":3.7,"Aged 5 to 9 years (number)":351,"Aged 5 to 9 years (%)":3.6,"Aged 10 to 15 years (number)":432,"Aged 10 to 15 years (%)":4.4,"Aged 16 to 19 years (number)":274,"Aged 16 to 19 years (%)":2.8,"Aged 20 to 24 years (number)":1308,"Aged 20 to 24 years (%)":13.3,"Aged 25 to 34 years (number)":3434,"Aged 25 to 34 years (%)":34.9,"Aged 35 to 49 years (number)":1646,"Aged 35 to 49 years (%)":16.7,"Aged 50 to 64 years (number)":1335,"Aged 50 to 64 years (%)":13.6,"Aged 65 to 74 years (number)":378,"Aged 65 to 74 years (%)":3.8,"Aged 75 to 84 years (number)":219,"Aged 75 to 84 years (%)":2.2,"Aged 85 years and over (number)":102,"Aged 85 years and over (%)":1},{"AreaName":"Clapham Park","Aged 4 years and under (number)":586,"Aged 4 years and under (%)":4.6,"Aged 5 to 9 years (number)":568,"Aged 5 to 9 years (%)":4.5,"Aged 10 to 15 years (number)":694,"Aged 10 to 15 years (%)":5.5,"Aged 16 to 19 years (number)":450,"Aged 16 to 19 years (%)":3.5,"Aged 20 to 24 years (number)":1121,"Aged 20 to 24 years (%)":8.8,"Aged 25 to 34 years (number)":3546,"Aged 25 to 34 years (%)":27.9,"Aged 35 to 49 years (number)":2791,"Aged 35 to 49 years (%)":22,"Aged 50 to 64 years (number)":2042,"Aged 50 to 64 years (%)":16.1,"Aged 65 to 74 years (number)":535,"Aged 65 to 74 years (%)":4.2,"Aged 75 to 84 years (number)":282,"Aged 75 to 84 years (%)":2.2,"Aged 85 years and over (number)":100,"Aged 85 years and over (%)":0.8},{"AreaName":"Clapham Town","Aged 4 years and under (number)":605,"Aged 4 years and under (%)":3.8,"Aged 5 to 9 years (number)":627,"Aged 5 to 9 years (%)":3.9,"Aged 10 to 15 years (number)":672,"Aged 10 to 15 years (%)":4.2,"Aged 16 to 19 years (number)":368,"Aged 16 to 19 years (%)":2.3,"Aged 20 to 24 years (number)":1681,"Aged 20 to 24 years (%)":10.6,"Aged 25 to 34 years (number)":5111,"Aged 25 to 34 years (%)":32.1,"Aged 35 to 49 years (number)":3194,"Aged 35 to 49 years (%)":20.1,"Aged 50 to 64 years (number)":2309,"Aged 50 to 64 years (%)":14.5,"Aged 65 to 74 years (number)":774,"Aged 65 to 74 years (%)":4.9,"Aged 75 to 84 years (number)":420,"Aged 75 to 84 years (%)":2.6,"Aged 85 years and over (number)":142,"Aged 85 years and over (%)":0.9},{"AreaName":"Gipsy Hill","Aged 4 years and under (number)":697,"Aged 4 years and under (%)":6.8,"Aged 5 to 9 years (number)":670,"Aged 5 to 9 years (%)":6.5,"Aged 10 to 15 years (number)":768,"Aged 10 to 15 years (%)":7.5,"Aged 16 to 19 years (number)":444,"Aged 16 to 19 years (%)":4.3,"Aged 20 to 24 years (number)":485,"Aged 20 to 24 years (%)":4.7,"Aged 25 to 34 years (number)":1908,"Aged 25 to 34 years (%)":18.6,"Aged 35 to 49 years (number)":2521,"Aged 35 to 49 years (%)":24.6,"Aged 50 to 64 years (number)":1813,"Aged 50 to 64 years (%)":17.7,"Aged 65 to 74 years (number)":574,"Aged 65 to 74 years (%)":5.6,"Aged 75 to 84 years (number)":283,"Aged 75 to 84 years (%)":2.8,"Aged 85 years and over (number)":98,"Aged 85 years and over (%)":1},{"AreaName":"Herne Hill & Loughborough Junction","Aged 4 years and under (number)":810,"Aged 4 years and under (%)":5,"Aged 5 to 9 years (number)":782,"Aged 5 to 9 years (%)":4.8,"Aged 10 to 15 years (number)":1002,"Aged 10 to 15 years (%)":6.2,"Aged 16 to 19 years (number)":685,"Aged 16 to 19 years (%)":4.2,"Aged 20 to 24 years (number)":1219,"Aged 20 to 24 years (%)":7.5,"Aged 25 to 34 years (number)":4163,"Aged 25 to 34 years (%)":25.8,"Aged 35 to 49 years (number)":3448,"Aged 35 to 49 years (%)":21.3,"Aged 50 to 64 years (number)":2751,"Aged 50 to 64 years (%)":17,"Aged 65 to 74 years (number)":802,"Aged 65 to 74 years (%)":5,"Aged 75 to 84 years (number)":379,"Aged 75 to 84 years (%)":2.3,"Aged 85 years and over (number)":117,"Aged 85 years and over (%)":0.7},{"AreaName":"Kennington","Aged 4 years and under (number)":673,"Aged 4 years and under (%)":4.6,"Aged 5 to 9 years (number)":690,"Aged 5 to 9 years (%)":4.7,"Aged 10 to 15 years (number)":933,"Aged 10 to 15 years (%)":6.4,"Aged 16 to 19 years (number)":561,"Aged 16 to 19 years (%)":3.8,"Aged 20 to 24 years (number)":1195,"Aged 20 to 24 years (%)":8.2,"Aged 25 to 34 years (number)":3258,"Aged 25 to 34 years (%)":22.3,"Aged 35 to 49 years (number)":3065,"Aged 35 to 49 years (%)":21,"Aged 50 to 64 years (number)":2721,"Aged 50 to 64 years (%)":18.6,"Aged 65 to 74 years (number)":894,"Aged 65 to 74 years (%)":6.1,"Aged 75 to 84 years (number)":450,"Aged 75 to 84 years (%)":3.1,"Aged 85 years and over (number)":153,"Aged 85 years and over (%)":1},{"AreaName":"Knight's Hill","Aged 4 years and under (number)":1092,"Aged 4 years and under (%)":6.5,"Aged 5 to 9 years (number)":1080,"Aged 5 to 9 years (%)":6.4,"Aged 10 to 15 years (number)":1279,"Aged 10 to 15 years (%)":7.6,"Aged 16 to 19 years (number)":740,"Aged 16 to 19 years (%)":4.4,"Aged 20 to 24 years (number)":911,"Aged 20 to 24 years (%)":5.4,"Aged 25 to 34 years (number)":2795,"Aged 25 to 34 years (%)":16.5,"Aged 35 to 49 years (number)":4046,"Aged 35 to 49 years (%)":23.9,"Aged 50 to 64 years (number)":3274,"Aged 50 to 64 years (%)":19.4,"Aged 65 to 74 years (number)":960,"Aged 65 to 74 years (%)":5.7,"Aged 75 to 84 years (number)":530,"Aged 75 to 84 years (%)":3.1,"Aged 85 years and over (number)":192,"Aged 85 years and over (%)":1.1},{"AreaName":"Myatt's Fields","Aged 4 years and under (number)":512,"Aged 4 years and under (%)":4.7,"Aged 5 to 9 years (number)":520,"Aged 5 to 9 years (%)":4.8,"Aged 10 to 15 years (number)":695,"Aged 10 to 15 years (%)":6.4,"Aged 16 to 19 years (number)":462,"Aged 16 to 19 years (%)":4.2,"Aged 20 to 24 years (number)":887,"Aged 20 to 24 years (%)":8.1,"Aged 25 to 34 years (number)":2604,"Aged 25 to 34 years (%)":23.8,"Aged 35 to 49 years (number)":2333,"Aged 35 to 49 years (%)":21.3,"Aged 50 to 64 years (number)":1955,"Aged 50 to 64 years (%)":17.9,"Aged 65 to 74 years (number)":611,"Aged 65 to 74 years (%)":5.6,"Aged 75 to 84 years (number)":263,"Aged 75 to 84 years (%)":2.4,"Aged 85 years and over (number)":91,"Aged 85 years and over (%)":0.8},{"AreaName":"Oval","Aged 4 years and under (number)":466,"Aged 4 years and under (%)":3.7,"Aged 5 to 9 years (number)":415,"Aged 5 to 9 years (%)":3.3,"Aged 10 to 15 years (number)":539,"Aged 10 to 15 years (%)":4.3,"Aged 16 to 19 years (number)":497,"Aged 16 to 19 years (%)":4,"Aged 20 to 24 years (number)":1278,"Aged 20 to 24 years (%)":10.3,"Aged 25 to 34 years (number)":3649,"Aged 25 to 34 years (%)":29.3,"Aged 35 to 49 years (number)":2423,"Aged 35 to 49 years (%)":19.5,"Aged 50 to 64 years (number)":1935,"Aged 50 to 64 years (%)":15.6,"Aged 65 to 74 years (number)":684,"Aged 65 to 74 years (%)":5.5,"Aged 75 to 84 years (number)":383,"Aged 75 to 84 years (%)":3.1,"Aged 85 years and over (number)":168,"Aged 85 years and over (%)":1.4},{"AreaName":"St Martin's","Aged 4 years and under (number)":577,"Aged 4 years and under (%)":5.3,"Aged 5 to 9 years (number)":612,"Aged 5 to 9 years (%)":5.6,"Aged 10 to 15 years (number)":837,"Aged 10 to 15 years (%)":7.7,"Aged 16 to 19 years (number)":514,"Aged 16 to 19 years (%)":4.7,"Aged 20 to 24 years (number)":719,"Aged 20 to 24 years (%)":6.6,"Aged 25 to 34 years (number)":2278,"Aged 25 to 34 years (%)":21,"Aged 35 to 49 years (number)":2634,"Aged 35 to 49 years (%)":24.3,"Aged 50 to 64 years (number)":1952,"Aged 50 to 64 years (%)":18,"Aged 65 to 74 years (number)":456,"Aged 65 to 74 years (%)":4.2,"Aged 75 to 84 years (number)":193,"Aged 75 to 84 years (%)":1.8,"Aged 85 years and over (number)":71,"Aged 85 years and over (%)":0.7},{"AreaName":"Stockwell East","Aged 4 years and under (number)":429,"Aged 4 years and under (%)":4,"Aged 5 to 9 years (number)":404,"Aged 5 to 9 years (%)":3.8,"Aged 10 to 15 years (number)":476,"Aged 10 to 15 years (%)":4.4,"Aged 16 to 19 years (number)":319,"Aged 16 to 19 years (%)":3,"Aged 20 to 24 years (number)":994,"Aged 20 to 24 years (%)":9.2,"Aged 25 to 34 years (number)":3357,"Aged 25 to 34 years (%)":31.2,"Aged 35 to 49 years (number)":2220,"Aged 35 to 49 years (%)":20.6,"Aged 50 to 64 years (number)":1706,"Aged 50 to 64 years (%)":15.9,"Aged 65 to 74 years (number)":499,"Aged 65 to 74 years (%)":4.6,"Aged 75 to 84 years (number)":240,"Aged 75 to 84 years (%)":2.2,"Aged 85 years and over (number)":107,"Aged 85 years and over (%)":1},{"AreaName":"Stockwell West & Larkhall","Aged 4 years and under (number)":684,"Aged 4 years and under (%)":4.2,"Aged 5 to 9 years (number)":793,"Aged 5 to 9 years (%)":4.9,"Aged 10 to 15 years (number)":1135,"Aged 10 to 15 years (%)":6.9,"Aged 16 to 19 years (number)":672,"Aged 16 to 19 years (%)":4.1,"Aged 20 to 24 years (number)":1494,"Aged 20 to 24 years (%)":9.1,"Aged 25 to 34 years (number)":4090,"Aged 25 to 34 years (%)":25,"Aged 35 to 49 years (number)":3427,"Aged 35 to 49 years (%)":21,"Aged 50 to 64 years (number)":2847,"Aged 50 to 64 years (%)":17.4,"Aged 65 to 74 years (number)":730,"Aged 65 to 74 years (%)":4.5,"Aged 75 to 84 years (number)":320,"Aged 75 to 84 years (%)":2,"Aged 85 years and over (number)":141,"Aged 85 years and over (%)":0.9},{"AreaName":"Streatham Common & Vale","Aged 4 years and under (number)":1042,"Aged 4 years and under (%)":5.9,"Aged 5 to 9 years (number)":908,"Aged 5 to 9 years (%)":5.1,"Aged 10 to 15 years (number)":1190,"Aged 10 to 15 years (%)":6.7,"Aged 16 to 19 years (number)":687,"Aged 16 to 19 years (%)":3.9,"Aged 20 to 24 years (number)":1052,"Aged 20 to 24 years (%)":6,"Aged 25 to 34 years (number)":3449,"Aged 25 to 34 years (%)":19.5,"Aged 35 to 49 years (number)":4216,"Aged 35 to 49 years (%)":23.9,"Aged 50 to 64 years (number)":3011,"Aged 50 to 64 years (%)":17.1,"Aged 65 to 74 years (number)":1171,"Aged 65 to 74 years (%)":6.6,"Aged 75 to 84 years (number)":663,"Aged 75 to 84 years (%)":3.8,"Aged 85 years and over (number)":258,"Aged 85 years and over (%)":1.5},{"AreaName":"Streatham Hill East","Aged 4 years and under (number)":518,"Aged 4 years and under (%)":5.2,"Aged 5 to 9 years (number)":488,"Aged 5 to 9 years (%)":4.9,"Aged 10 to 15 years (number)":605,"Aged 10 to 15 years (%)":6.1,"Aged 16 to 19 years (number)":433,"Aged 16 to 19 years (%)":4.4,"Aged 20 to 24 years (number)":610,"Aged 20 to 24 years (%)":6.2,"Aged 25 to 34 years (number)":2328,"Aged 25 to 34 years (%)":23.6,"Aged 35 to 49 years (number)":2439,"Aged 35 to 49 years (%)":24.7,"Aged 50 to 64 years (number)":1567,"Aged 50 to 64 years (%)":15.9,"Aged 65 to 74 years (number)":452,"Aged 65 to 74 years (%)":4.6,"Aged 75 to 84 years (number)":274,"Aged 75 to 84 years (%)":2.8,"Aged 85 years and over (number)":162,"Aged 85 years and over (%)":1.6},{"AreaName":"Streatham Hill West & Thornton","Aged 4 years and under (number)":654,"Aged 4 years and under (%)":6,"Aged 5 to 9 years (number)":596,"Aged 5 to 9 years (%)":5.5,"Aged 10 to 15 years (number)":580,"Aged 10 to 15 years (%)":5.3,"Aged 16 to 19 years (number)":289,"Aged 16 to 19 years (%)":2.7,"Aged 20 to 24 years (number)":676,"Aged 20 to 24 years (%)":6.2,"Aged 25 to 34 years (number)":3095,"Aged 25 to 34 years (%)":28.4,"Aged 35 to 49 years (number)":2602,"Aged 35 to 49 years (%)":23.9,"Aged 50 to 64 years (number)":1532,"Aged 50 to 64 years (%)":14.1,"Aged 65 to 74 years (number)":495,"Aged 65 to 74 years (%)":4.5,"Aged 75 to 84 years (number)":283,"Aged 75 to 84 years (%)":2.6,"Aged 85 years and over (number)":88,"Aged 85 years and over (%)":0.8},{"AreaName":"Streatham St Leonard's","Aged 4 years and under (number)":925,"Aged 4 years and under (%)":5.8,"Aged 5 to 9 years (number)":839,"Aged 5 to 9 years (%)":5.3,"Aged 10 to 15 years (number)":918,"Aged 10 to 15 years (%)":5.8,"Aged 16 to 19 years (number)":471,"Aged 16 to 19 years (%)":3,"Aged 20 to 24 years (number)":930,"Aged 20 to 24 years (%)":5.9,"Aged 25 to 34 years (number)":3897,"Aged 25 to 34 years (%)":24.6,"Aged 35 to 49 years (number)":4087,"Aged 35 to 49 years (%)":25.8,"Aged 50 to 64 years (number)":2391,"Aged 50 to 64 years (%)":15.1,"Aged 65 to 74 years (number)":741,"Aged 65 to 74 years (%)":4.7,"Aged 75 to 84 years (number)":438,"Aged 75 to 84 years (%)":2.8,"Aged 85 years and over (number)":179,"Aged 85 years and over (%)":1.1},{"AreaName":"Streatham Wells","Aged 4 years and under (number)":532,"Aged 4 years and under (%)":5.5,"Aged 5 to 9 years (number)":536,"Aged 5 to 9 years (%)":5.5,"Aged 10 to 15 years (number)":554,"Aged 10 to 15 years (%)":5.7,"Aged 16 to 19 years (number)":300,"Aged 16 to 19 years (%)":3.1,"Aged 20 to 24 years (number)":510,"Aged 20 to 24 years (%)":5.2,"Aged 25 to 34 years (number)":2324,"Aged 25 to 34 years (%)":23.8,"Aged 35 to 49 years (number)":2464,"Aged 35 to 49 years (%)":25.2,"Aged 50 to 64 years (number)":1561,"Aged 50 to 64 years (%)":16,"Aged 65 to 74 years (number)":540,"Aged 65 to 74 years (%)":5.5,"Aged 75 to 84 years (number)":300,"Aged 75 to 84 years (%)":3.1,"Aged 85 years and over (number)":140,"Aged 85 years and over (%)":1.4},{"AreaName":"Vauxhall","Aged 4 years and under (number)":365,"Aged 4 years and under (%)":3.7,"Aged 5 to 9 years (number)":315,"Aged 5 to 9 years (%)":3.2,"Aged 10 to 15 years (number)":389,"Aged 10 to 15 years (%)":4,"Aged 16 to 19 years (number)":380,"Aged 16 to 19 years (%)":3.9,"Aged 20 to 24 years (number)":1334,"Aged 20 to 24 years (%)":13.7,"Aged 25 to 34 years (number)":2868,"Aged 25 to 34 years (%)":29.5,"Aged 35 to 49 years (number)":2062,"Aged 35 to 49 years (%)":21.2,"Aged 50 to 64 years (number)":1385,"Aged 50 to 64 years (%)":14.2,"Aged 65 to 74 years (number)":371,"Aged 65 to 74 years (%)":3.8,"Aged 75 to 84 years (number)":192,"Aged 75 to 84 years (%)":2,"Aged 85 years and over (number)":77,"Aged 85 years and over (%)":0.8},{"AreaName":"Waterloo & South Bank","Aged 4 years and under (number)":247,"Aged 4 years and under (%)":2.8,"Aged 5 to 9 years (number)":262,"Aged 5 to 9 years (%)":3,"Aged 10 to 15 years (number)":347,"Aged 10 to 15 years (%)":3.9,"Aged 16 to 19 years (number)":717,"Aged 16 to 19 years (%)":8.1,"Aged 20 to 24 years (number)":1460,"Aged 20 to 24 years (%)":16.5,"Aged 25 to 34 years (number)":2067,"Aged 25 to 34 years (%)":23.3,"Aged 35 to 49 years (number)":1643,"Aged 35 to 49 years (%)":18.5,"Aged 50 to 64 years (number)":1249,"Aged 50 to 64 years (%)":14.1,"Aged 65 to 74 years (number)":512,"Aged 65 to 74 years (%)":5.8,"Aged 75 to 84 years (number)":258,"Aged 75 to 84 years (%)":2.9,"Aged 85 years and over (number)":97,"Aged 85 years and over (%)":1.1},{"AreaName":"West Dulwich","Aged 4 years and under (number)":676,"Aged 4 years and under (%)":5.9,"Aged 5 to 9 years (number)":690,"Aged 5 to 9 years (%)":6.1,"Aged 10 to 15 years (number)":860,"Aged 10 to 15 years (%)":7.6,"Aged 16 to 19 years (number)":406,"Aged 16 to 19 years (%)":3.6,"Aged 20 to 24 years (number)":517,"Aged 20 to 24 years (%)":4.5,"Aged 25 to 34 years (number)":2041,"Aged 25 to 34 years (%)":17.9,"Aged 35 to 49 years (number)":2811,"Aged 35 to 49 years (%)":24.7,"Aged 50 to 64 years (number)":2008,"Aged 50 to 64 years (%)":17.6,"Aged 65 to 74 years (number)":826,"Aged 65 to 74 years (%)":7.3,"Aged 75 to 84 years (number)":401,"Aged 75 to 84 years (%)":3.5,"Aged 85 years and over (number)":148,"Aged 85 years and over (%)":1.3},{"AreaName":"England","Aged 4 years and under (number)":3076950,"Aged 4 years and under (%)":5.4,"Aged 5 to 9 years (number)":3348701,"Aged 5 to 9 years (%)":5.9,"Aged 10 to 15 years (number)":4057443,"Aged 10 to 15 years (%)":7.2,"Aged 16 to 19 years (number)":2574781,"Aged 16 to 19 years (%)":4.6,"Aged 20 to 24 years (number)":3414450,"Aged 20 to 24 years (%)":6,"Aged 25 to 34 years (number)":7667865,"Aged 25 to 34 years (%)":13.6,"Aged 35 to 49 years (number)":10978437,"Aged 35 to 49 years (%)":19.4,"Aged 50 to 64 years (number)":10970118,"Aged 50 to 64 years (%)":19.4,"Aged 65 to 74 years (number)":5564143,"Aged 65 to 74 years (%)":9.8,"Aged 75 to 84 years (number)":3464857,"Aged 75 to 84 years (%)":6.1,"Aged 85 years and over (number)":1372300,"Aged 85 years and over (%)":2.4},{"AreaName":"London","Aged 4 years and under (number)":528953,"Aged 4 years and under (%)":6,"Aged 5 to 9 years (number)":531496,"Aged 5 to 9 years (%)":6,"Aged 10 to 15 years (number)":635291,"Aged 10 to 15 years (%)":7.2,"Aged 16 to 19 years (number)":389537,"Aged 16 to 19 years (%)":4.4,"Aged 20 to 24 years (number)":589185,"Aged 20 to 24 years (%)":6.7,"Aged 25 to 34 years (number)":1594891,"Aged 25 to 34 years (%)":18.1,"Aged 35 to 49 years (number)":1996961,"Aged 35 to 49 years (%)":22.7,"Aged 50 to 64 years (number)":1489993,"Aged 50 to 64 years (%)":16.9,"Aged 65 to 74 years (number)":575478,"Aged 65 to 74 years (%)":6.5,"Aged 75 to 84 years (number)":330329,"Aged 75 to 84 years (%)":3.8,"Aged 85 years and over (number)":137609,"Aged 85 years and over (%)":1.6}]